{
  "file": "academy/jedi_oring_qwer.json",
  "accountId": "oring",
  "id": "jedi_oring_qwer",
  "name": "qwer",
  "title": "Jedi Youngling",
  "species": "Human",
  "dob": "2026-07-04",
  "gender": "Any",
  "height": "1.65m",
  "affiliation": "Jedi Academy",
  "lastDayTrained": "2026-07-04T18:00:46.801Z",
  "lightsaber": {
    "color": "blue",
    "crystal": "Kyber Crystal",
    "hiltStyle": "Academy Standard",
    "form": "Form I: Shii-Cho",
    "status": "Fully Operational"
  },
  "stats": {
    "forcePower": 29,
    "lightsaberSkill": 40,
    "agility": 25,
    "wisdom": 26,
    "strength": 70,
    "defense": 70
  },
  "combatRecord": {
    "wins": 0,
    "losses": 1,
    "draws": 0,
    "totalDuels": 1
  },
  "ranking": {
    "title": "Jedi Youngling",
    "achievementPoints": 120,
    "galacticRank": 99
  },
  "forcePower": 29,
  "lightsaberSkill": 40,
  "agility": 25,
  "wisdom": 26,
  "wins": 0,
  "losses": 1,
  "score": 120,
  "rank": "Youngling",
  "lightsaberColor": "blue",
  "avatarSeed": "jedi_1783186991427_qwer",
  "lightsaberForm": "Form I: Shii-Cho",
  "creds": 91,
  "questProgress": [
    "quest1-c"
  ],
  "quest1Count": 1,
  "isPlayerCustom": true
}